PEALS/__init__.py
PEALS/collection/__init__.py
PEALS/collection/bamtool.py
PEALS/collection/bedutils.py
PEALS/collection/functools.py
PEALS/collection/gfftools.py
PEALS/collection/optioncheck.py
PEALS/io/__init__.py
PEALS/io/constant.py
PEALS/io/paramlog.py
PEALS/io/report.py
PEALS/io/signals.py
PEALS/io/streamtools.py
PEALS/peak/__init__.py
PEALS/peak/peakcall.py
PEALS/peak/peakutils.py
PEALS/stats/__init__.py
PEALS/stats/correction.py
PEALS/stats/peaktest.py
PEALS/stats/runGlmNbinomTest.R
PEALS/stats/statstools.py
PEALS/subcmd/__init__.py
PEALS/subcmd/callpeak_cmd.py
PEALS/subcmd/diffpeak_cmd.py
PEALS-1.2.5.data/scripts/peals
PEALS-1.2.5.dist-info/METADATA
PEALS-1.2.5.dist-info/WHEEL
PEALS-1.2.5.dist-info/top_level.txt
PEALS-1.2.5.dist-info/RECORD
