Metadata-Version: 2.1
Name: PEALS
Version: 1.2.5
Summary: Peak-based Enhancement Analysis PipeLine for MeRIP-seq
Home-page: http://github.com/kerenzhou062/PEALS/
Author: Keren Zhou
Author-email: Keren Zhou <zhoukr062@gmail.com>
Project-URL: Homepage, https://github.com/kerenzhou062/PEALS
Project-URL: Bug Tracker, https://github.com/kerenzhou062/PEALS/issues
Classifier: Programming Language :: Python :: 3
Classifier: License :: OSI Approved :: MIT License
Classifier: Operating System :: OS Independent
Requires-Python: >=3.8
Requires-Dist: numpy >=1.21.2
Requires-Dist: pandas >=1.1.4
Requires-Dist: scipy >=1.7.1
Requires-Dist: pysam >=0.16.0.1
Requires-Dist: psutil >=5.9.4
Requires-Dist: pyBigWig >=0.3.18
Requires-Dist: tqdm >=4.64.1
Requires-Dist: tabulate >=0.8.7
Requires-Dist: rpy2 ==3.4.5
Requires-Dist: mpmath >=1.1.0
Requires-Dist: findpeaks >=2.4.6
Requires-Dist: csaps >=1.1.0
Requires-Dist: bottleneck >=1.3.2
Requires-Dist: scikit-learn >=0.24.2
Requires-Dist: networkx >=2.5.1
Requires-Dist: fisher >=0.1.10
Requires-Dist: setuptools >=45.2.0
Requires-Dist: pytest >=5.4.1
